cumulus_library_catalog/__init__.py
cumulus_library_catalog/manifest.toml
cumulus_library_catalog/catalog/__init__.py
cumulus_library_catalog/catalog/icd10_annotated_counts.py
cumulus_library_catalog/catalog/meta.sql
cumulus_library_catalog/reference_sql/icd10_annotated_counts.sql
cumulus_library_catalog-0.2.2.dist-info/licenses/LICENSE
cumulus_library_catalog-0.2.2.dist-info/WHEEL
cumulus_library_catalog-0.2.2.dist-info/METADATA
cumulus_library_catalog-0.2.2.dist-info/RECORD
