Metadata-Version: 2.4
Name: cumulus-library-catalog
Version: 0.2.2
Summary: Catalog hierarchies for Dx, Rx, Labs, and other FHIR resource types
Requires-Python: >= 3.11
Classifier: License :: OSI Approved :: Apache Software License
Classifier: Operating System :: OS Independent
Classifier: Programming Language :: Python :: 3
Classifier: Topic :: Software Development :: Libraries :: Python Modules
License-File: LICENSE
Requires-Dist: cumulus-library >= 5, <6
Requires-Dist: sqlfluff >=3
Requires-Dist: xlrd
Requires-Dist: openpyxl
Requires-Dist: pandas
Requires-Dist: ruff < 0.13 ; extra == "dev"
Requires-Dist: pylint ; extra == "dev"
Requires-Dist: sqlfluff > 3, <4 ; extra == "dev"
Requires-Dist: pytest ; extra == "test"
Requires-Dist: pytest-cov ; extra == "test"
Project-URL: Documentation, https://docs.smarthealthit.org/cumulus/
Project-URL: Home, https://smarthealthit.org/cumulus/
Project-URL: Source, https://github.com/smart-on-fhir/cumulus-library-catalog
Provides-Extra: dev
Provides-Extra: test
